django_csv_utils/__init__.py
django_csv_utils/exceptions.py
django_csv_utils/imports.py
django_csv_utils/management.py
django_csv_utils/utils.py
django_csv_utils/views.py
django_csv_utils-1.0.2.dist-info/DESCRIPTION.rst
django_csv_utils-1.0.2.dist-info/METADATA
django_csv_utils-1.0.2.dist-info/RECORD
django_csv_utils-1.0.2.dist-info/WHEEL
django_csv_utils-1.0.2.dist-info/metadata.json
django_csv_utils-1.0.2.dist-info/top_level.txt
