Metadata-Version: 2.0
Name: django-csv-utils
Version: 1.0.2
Summary: Utilities for working with CSVs in Django
Home-page: https://github.com/ionata/django-csv-utils
Author: Ionata Digital
Author-email: webmaster@ionata.com.au
License: UNKNOWN
Platform: UNKNOWN
Classifier: Environment :: Web Environment
Classifier: Intended Audience :: Developers
Classifier: Operating System :: OS Independent
Classifier: Programming Language :: Python
Classifier: Framework :: Django
Requires-Dist: django (>=1.8.0)
